dc_python_sdk-1.4.3.1.dist-info/licenses/LICENSE
dc_sdk/__init__.py
dc_sdk/conftest.py
dc_sdk/errors.py
dc_sdk/pytest.txt
dc_sdk/test_connector.py
dc_python_sdk-1.4.3.1.dist-info/METADATA
dc_python_sdk-1.4.3.1.dist-info/WHEEL
dc_python_sdk-1.4.3.1.dist-info/top_level.txt
dc_python_sdk-1.4.3.1.dist-info/RECORD
