Metadata-Version: 2.4
Name: dc-python-sdk
Version: 1.4.3.1
Summary: A small example package
Home-page: https://github.com/data-connector/dc-python-sdk
Author: DataConnector
Author-email: josh@dataconnector.com
Project-URL: Bug Tracker, https://github.com/data-connector/dc-python-sdk/issues
Classifier: Programming Language :: Python :: 3
Classifier: License :: OSI Approved :: MIT License
Classifier: Operating System :: OS Independent
Requires-Python: >=3.6
License-File: LICENSE
Dynamic: license-file
